Workbook
Name Slicer_Region: #N/A

Sheet Data
B2: Retailer Dataset
B4: Retailer | C4: Retailer ID | D4: Invoice Date | E4: Region | F4: State | G4: City | H4: Beverage Brand | I4: Price per Unit | J4: Units Sold | K4: Total Sales | L4: Operating Profit | M4: Operating Margin
B5: BevCo | C5: 1185732 | D5: 44562 | E5: Northeast | F5: New York | G5: New York | H5: Coca-Cola | I5: 0.5 | J5: 12000 | K5: 6000 | L5: 3000 | M5: 0.5
B6: BevCo | C6: 1185732 | D6: 44563 | E6: Northeast | F6: New York | G6: New York | H6: Diet Coke | I6: 0.5 | J6: 10000 | K6: 5000 | L6: 1500 | M6: 0.3
B7: BevCo | C7: 1185732 | D7: 44564 | E7: Northeast | F7: New York | G7: New York | H7: Sprite | I7: 0.4 | J7: 10000 | K7: 4000 | L7: 1400 | M7: 0.35
B8: BevCo | C8: 1185732 | D8: 44565 | E8: Northeast | F8: New York | G8: New York | H8: Fanta | I8: 0.45 | J8: 8500 | K8: 3825 | L8: 1338.75 | M8: 0.35
B9: BevCo | C9: 1185732 | D9: 44566 | E9: Northeast | F9: New York | G9: New York | H9: Powerade | I9: 0.6 | J9: 9000 | K9: 5400 | L9: 1620 | M9: 0.3
B10: BevCo | C10: 1185732 | D10: 44567 | E10: Northeast | F10: New York | G10: New York | H10: Dasani Water | I10: 0.5 | J10: 10000 | K10: 5000 | L10: 1250 | M10: 0.25
B11: BevCo | C11: 1185732 | D11: 44568 | E11: Northeast | F11: New York | G11: New York | H11: Coca-Cola | I11: 0.5 | J11: 12500 | K11: 6250 | L11: 3125 | M11: 0.5
B12: BevCo | C12: 1185732 | D12: 44569 | E12: Northeast | F12: New York | G12: New York | H12: Diet Coke | I12: 0.5 | J12: 9000 | K12: 4500 | L12: 1350 | M12: 0.3
B13: BevCo | C13: 1185732 | D13: 44582 | E13: Northeast | F13: New York | G13: New York | H13: Sprite | I13: 0.4 | J13: 9500 | K13: 3800 | L13: 1330 | M13: 0.35
B14: BevCo | C14: 1185732 | D14: 44583 | E14: Northeast | F14: New York | G14: New York | H14: Fanta | I14: 0.45 | J14: 8250 | K14: 3712.5 | L14: 1299.375 | M14: 0.35
B15: BevCo | C15: 1185732 | D15: 44584 | E15: Northeast | F15: New York | G15: New York | H15: Powerade | I15: 0.6 | J15: 9000 | K15: 5400 | L15: 1620 | M15: 0.3
B16: BevCo | C16: 1185732 | D16: 44585 | E16: Northeast | F16: New York | G16: New York | H16: Dasani Water | I16: 0.5 | J16: 10000 | K16: 5000 | L16: 1250 | M16: 0.25
... B9652: BevCo | C9652: 1185732 | D9652: 44979 | E9652: Northeast | F9652: New Hampshire | G9652: Manchester | H9652: Sprite | I9652: 0.29 | J9652: 830 | K9652: 240.7 | L9652: 64.989 | M9652: 0.27

Sheet Analyze
A1: KPI's | B1: Total Sales | D1: Total Profit | F1: Total Profit Margin | G1: Average Profit Margin
B4: Sum of Total Sales | D4: Sum of Operating Profit | F4: Sum of Operating Profit | G4: Average of Operating Margin | J4: Average of Operating Profit | M4: Sum of Units Sold
B5: 12016665 | D5: 4722496.8 | F5: 4722496.8 | G5: 0.42299129 | J5: 489.47935 | M5: 24788610
B10: Sum of Total Sales | C10: Column Labels
B11: Row Labels | C11: 2022 | D11: 2023
B12: West Soda | C12: 1170361.6 | D12: 2070594.2 | E12: =B12 -> West Soda | F12: =C12 -> 1170361.6 | G12: =D12 -> 2070594.2
B13: Walmart | C13: 339912.5 | D13: 580211 | E13: =B13 -> Walmart | F13: =C13 -> 339912.5 | G13: =D13 -> 580211
B14: Target | C14: 9250.3 | D14: 1341995 | E14: =B14 -> Target | F14: =C14 -> 9250.3 | G14: =D14 -> 1341995
B15: FizzyCo | C15: 161210.1 | D15: 2262827.1 | E15: =B15 -> FizzyCo | F15: =C15 -> 161210.1 | G15: =D15 -> 2262827.1
B16: BevCo | C16: 466788 | D16: 2327606.5 | E16: =B16 -> BevCo | F16: =C16 -> 466788 | G16: =D16 -> 2327606.5
B17: Amazon | C17: 276210 | D17: 1009698.7 | E17: =B17 -> Amazon | F17: =C17 -> 276210 | G17: =D17 -> 1009698.7
B21: Row Labels | C21: Total Retailer Sales | D21: Average of Operating Profit
B22: 2022 | C22: 90391.8 | D22: 241.15435 | E22: =B22 -> 2022 | F22: =B23 -> Qtr4 | G22: =C23 -> 90391.8 | H22: =D23 -> 241.15435
B23: Qtr4 | C23: 90391.8 | D23: 241.15435 | F23: =B24 -> 2023 | G23: =C24 -> 1577051.6 | H23: =D24 -> 376.89138
B24: 2023 | C24: 1577051.6 | D24: 376.89138 | F24: =B25 -> Qtr1 | G24: =C25 -> 383459.1 | H24: =D25 -> 338.11582
B25: Qtr1 | C25: 383459.1 | D25: 338.11582 | F25: =B26 -> Qtr2 | G25: =C26 -> 355718.2 | H25: =D26 -> 327.64214
B26: Qtr2 | C26: 355718.2 | D26: 327.64214 | E26: =B27 -> Qtr3 | F26: =B28 -> Qtr4 | G26: =C28 -> 354252.3 | H26: =D28 -> 447.28746
B27: Qtr3 | C27: 483622 | D27: 413.25352 | F27: =B29 -> 0 | G27: =C29 -> 0 | H27: =D29 -> 0
B28: Qtr4 | C28: 354252.3 | D28: 447.28746 | F28: =B30 -> 0 | G28: =C30 -> 0 | H28: =D30 -> 0
F29: =B31 -> 0 | G29: =C31 -> 0 | H29: =D31 -> 0
A52: Sum of Total Sales | B52: Column Labels
A53: Row Labels | B53: 2022 | C53: 2023
A54: Coca-Cola | B54: 499102 | C54: 2268974.9 | D54: =A54 -> Coca-Cola | E54: =B54 -> 499102 | F54: =C54 -> 2268974.9
A55: Dasani Water | B55: 469270.7 | C55: 1917827.8 | D55: =A55 -> Dasani Water | E55: =B55 -> 469270.7 | F55: =C55 -> 1917827.8
A56: Diet Coke | B56: 423758.7 | C56: 1633959.3 | D56: =A56 -> Diet Coke | E56: =B56 -> 423758.7 | F56: =C56 -> 1633959.3
A57: Sprite | B57: 366578 | C57: 1353578.3 | D57: =A57 -> Sprite | E57: =B57 -> 366578 | F57: =C57 -> 1353578.3
A58: Powerade | B58: 349533.9 | C58: 1302529.3 | D58: =A58 -> Powerade | E58: =B58 -> 349533.9 | F58: =C58 -> 1302529.3
A59: Fanta | B59: 315489.2 | C59: 1116062.9 | D59: =A59 -> Fanta | E59: =B59 -> 315489.2 | F59: =C59 -> 1116062.9

Sheet Dashboard
C15: BRAND | D15: SALES 2022 | E15: SALES 2023 | F15: VARIANCE | H15: RETAILER | I15: SALES 2022 | J15: SALES 2023 | K15: VARIANCE
C16: =Analyze!E12 -> West Soda | D16: =Analyze!F12 -> 1170361.6 | E16: =Analyze!G12 -> 2070594.2 | F16: =E16-D16 -> 900232.6 | H16: =Analyze!D54 -> Coca-Cola | I16: =Analyze!E54 -> 499102 | J16: =Analyze!F54 -> 2268974.9 | K16: =J16-I16 -> 1769872.9
C17: =Analyze!E13 -> Walmart | D17: =Analyze!F13 -> 339912.5 | E17: =Analyze!G13 -> 580211 | F17: =E17-D17 -> 240298.5 | H17: =Analyze!D55 -> Dasani Water | I17: =Analyze!E55 -> 469270.7 | J17: =Analyze!F55 -> 1917827.8 | K17: =J17-I17 -> 1448557.1
C18: =Analyze!E14 -> Target | D18: =Analyze!F14 -> 9250.3 | E18: =Analyze!G14 -> 1341995 | F18: =E18-D18 -> 1332744.7 | H18: =Analyze!D56 -> Diet Coke | I18: =Analyze!E56 -> 423758.7 | J18: =Analyze!F56 -> 1633959.3 | K18: =J18-I18 -> 1210200.6
C19: =Analyze!E15 -> FizzyCo | D19: =Analyze!F15 -> 161210.1 | E19: =Analyze!G15 -> 2262827.1 | F19: =E19-D19 -> 2101617 | H19: =Analyze!D57 -> Sprite | I19: =Analyze!E57 -> 366578 | J19: =Analyze!F57 -> 1353578.3 | K19: =J19-I19 -> 987000.3
C20: =Analyze!E16 -> BevCo | D20: =Analyze!F16 -> 466788 | E20: =Analyze!G16 -> 2327606.5 | F20: =E20-D20 -> 1860818.5 | H20: =Analyze!D58 -> Powerade | I20: =Analyze!E58 -> 349533.9 | J20: =Analyze!F58 -> 1302529.3 | K20: =J20-I20 -> 952995.4
C21: =Analyze!E17 -> Amazon | D21: =Analyze!F17 -> 276210 | E21: =Analyze!G17 -> 1009698.7 | F21: =E21-D21 -> 733488.7 | H21: =Analyze!D59 -> Fanta | I21: =Analyze!E59 -> 315489.2 | J21: =Analyze!F59 -> 1116062.9 | K21: =J21-I21 -> 800573.7
C22: TOTAL | D22: =SUM(D16:D21) -> 2423732.5 | E22: =SUM(E16:E21) -> 9592932.5 | F22: =SUM(F16:F21) -> 7169200 | I22: =SUM(I16:I21) -> 2423732.5 | J22: =SUM(J16:J21) -> 9592932.5 | K22: =SUM(K16:K21) -> 7169200
